mcp_educate_time_zw_info/__init__.py
mcp_educate_time_zw_info/server.py
mcp_educate_time_zw_info-0.1.1.dist-info/METADATA
mcp_educate_time_zw_info-0.1.1.dist-info/WHEEL
mcp_educate_time_zw_info-0.1.1.dist-info/top_level.txt
mcp_educate_time_zw_info-0.1.1.dist-info/RECORD
