Metadata-Version: 2.1
Name: mcp-educate-time-zw-info
Version: 0.1.1
Summary: Add your description here
Home-page: https://github.com/users/wudidabo/projects/1
Author: wudidabo
Author-email: 2422994710@qq.com
Classifier: Programming Language :: Python :: 3
Classifier: License :: OSI Approved :: MIT License
Requires-Python: >=3.6
Requires-Dist: mcp[cli] (>=1.12.2)
Requires-Dist: setuptools (>=80.9.0)
Requires-Dist: twine (>=6.1.0)
Requires-Dist: wheel (>=0.45.1)
